pinnwand/__init__.py
pinnwand/__main__.py
pinnwand/command.py
pinnwand/configuration.py
pinnwand/database.py
pinnwand/defensive.py
pinnwand/error.py
pinnwand/handler/__init__.py
pinnwand/handler/api_curl.py
pinnwand/handler/api_deprecated.py
pinnwand/handler/api_v1.py
pinnwand/handler/website.py
pinnwand/http.py
pinnwand/page/about.rst
pinnwand/page/expiry.rst
pinnwand/page/removal.rst
pinnwand/path.py
pinnwand/static/favicon.png
pinnwand/static/logo.png
pinnwand/static/pinnwand.css
pinnwand/static/pinnwand.js
pinnwand/template/create.html
pinnwand/template/error.html
pinnwand/template/layout.html
pinnwand/template/part/lexer-select.html
pinnwand/template/restructuredtextpage.html
pinnwand/template/show.html
pinnwand/utility.py
pinnwand-1.5.0.dist-info/WHEEL
pinnwand-1.5.0.dist-info/METADATA
pinnwand-1.5.0.dist-info/licenses/LICENSE
pinnwand-1.5.0.dist-info/licenses/AUTHORS.rst
pinnwand-1.5.0.dist-info/RECORD
