Metadata-Version: 2.1
Name: pinnwand
Version: 1.5.0
Summary: Straightforward pastebin software.
License: MIT
Author-email: Simon de Vlieger <cmdr@supakeen.com>
Requires-Python: >=3.8
Requires-Dist: click>=8.1.3
Requires-Dist: docutils>=0.20.1
Requires-Dist: pygments-better-html>=0.1.4
Requires-Dist: pygments>=2.15.1
Requires-Dist: sqlalchemy>=2.0.15
Requires-Dist: token-bucket>=0.3.0
Requires-Dist: tomli>=2.0.1
Requires-Dist: tornado>=6.3.2
Provides-Extra: dev
Requires-Dist: pytest>=7.3.1; extra == "dev"
Requires-Dist: coverage>=7.2.7; extra == "dev"
Requires-Dist: black>=23.3.0; extra == "dev"
Requires-Dist: pytest-cov>=4.1.0; extra == "dev"
Requires-Dist: pre-commit>=3.3.2; extra == "dev"
Requires-Dist: mypy>=1.3.0; extra == "dev"
Requires-Dist: types-docutils>=0.20.0.1; extra == "dev"
Requires-Dist: isort>=5.12.0; extra == "dev"
Requires-Dist: bandit>=1.7.5; extra == "dev"
Requires-Dist: pip-audit>=2.5.6; extra == "dev"
Project-URL: Bug Tracker, https://github.com/supakeen/pinnwand/issues
Project-URL: Homepage, https://github.com/supakeen/pinnwand
Project-URL: Repository, https://github.com/supakeen/pinnwand
